arizona_forum_async/__init__.py
arizona_forum_async/api.py
arizona_forum_async/consts.py
arizona_forum_async/exceptions.py
arizona_forum_async/bypass_antibot/__init__.py
arizona_forum_async/bypass_antibot/script.py
arizona_forum_async/models/__init__.py
arizona_forum_async/models/category_object.py
arizona_forum_async/models/member_object.py
arizona_forum_async/models/other.py
arizona_forum_async/models/post_object.py
arizona_forum_async/models/thread_object.py
arizona_forum_api_async-1.4.2.dist-info/METADATA
arizona_forum_api_async-1.4.2.dist-info/WHEEL
arizona_forum_api_async-1.4.2.dist-info/top_level.txt
arizona_forum_api_async-1.4.2.dist-info/RECORD
