Metadata-Version: 2.4
Name: arizona-forum-api-async
Version: 1.4.2
Summary: Асинхронная Python библиотека для взаимодействия с форумом Arizona RP (forum.arizona-rp.com) без необходимости получения API ключа.
Home-page: https://github.com/fakelag28/Arizona-Forum-API-Async
Author: fakelag28
Author-email: fakelag712@gmail.com
Classifier: Programming Language :: Python :: 3
Classifier: License :: OSI Approved :: MIT License
Classifier: Operating System :: OS Independent
Requires-Python: >=3.6
Requires-Dist: aiohttp
Requires-Dist: aiohttp-socks
Requires-Dist: beautifulsoup4
Requires-Dist: dukpy
Requires-Dist: lxml
Dynamic: author
Dynamic: author-email
Dynamic: classifier
Dynamic: description
Dynamic: description-content-type
Dynamic: home-page
Dynamic: requires-dist
Dynamic: requires-python
Dynamic: summary
